transforms3d/__init__.py
transforms3d/_gohlketransforms.py
transforms3d/_version.py
transforms3d/affines.py
transforms3d/axangles.py
transforms3d/conftest.py
transforms3d/euler.py
transforms3d/quaternions.py
transforms3d/reflections.py
transforms3d/shears.py
transforms3d/taitbryan.py
transforms3d/testing.py
transforms3d/utils.py
transforms3d/zooms.py
transforms3d/derivations/__init__.py
transforms3d/derivations/angle_axes.py
transforms3d/derivations/decompositions.py
transforms3d/derivations/eulerangles.py
transforms3d/derivations/quaternions.py
transforms3d/derivations/utils.py
transforms3d/tests/__init__.py
transforms3d/tests/samples.py
transforms3d/tests/test_affines.py
transforms3d/tests/test_axangles.py
transforms3d/tests/test_euler.py
transforms3d/tests/test_implementations.py
transforms3d/tests/test_quaternions.py
transforms3d/tests/test_reflections.py
transforms3d/tests/test_taitbryan.py
transforms3d/tests/test_utils.py
transforms3d/tests/test_zooms_shears.py
transforms3d/tests/data/process_quats.m
transforms3d/tests/data/processed_quats.mat
transforms3d-0.4.2.dist-info/AUTHORS
transforms3d-0.4.2.dist-info/LICENSE
transforms3d-0.4.2.dist-info/METADATA
transforms3d-0.4.2.dist-info/WHEEL
transforms3d-0.4.2.dist-info/top_level.txt
transforms3d-0.4.2.dist-info/RECORD
