Metadata-Version: 2.1
Name: transforms3d
Version: 0.4.2
Summary: Functions for 3D coordinate transformations
Author-email: Matthew Brett <matthew.brett@gmail.com>
Maintainer-email: Matthew Brett <matthew.brett@gmail.com>
License: BSD license
Project-URL: Homepage, http://github.com/matthew-brett/transforms3d
Classifier: Development Status :: 4 - Beta
Classifier: Environment :: Console
Classifier: Intended Audience :: Developers
Classifier: Intended Audience :: Science/Research
Classifier: License :: OSI Approved :: BSD License
Classifier: Operating System :: MacOS
Classifier: Operating System :: Microsoft :: Windows
Classifier: Operating System :: POSIX
Classifier: Operating System :: Unix
Classifier: Programming Language :: Python
Classifier: Programming Language :: Python :: 3
Classifier: Topic :: Scientific/Engineering
Requires-Python: >=3.6
License-File: LICENSE
License-File: AUTHORS
Requires-Dist: numpy>=1.15
